ourpipes/__init__.py
ourpipes/framework.py
tests/__init__.py
tests/test_schema_execution.py
utils/__init__.py
utils/async_functools.py
ourpipes-0.0.5.dist-info/LICENSE
ourpipes-0.0.5.dist-info/METADATA
ourpipes-0.0.5.dist-info/WHEEL
ourpipes-0.0.5.dist-info/top_level.txt
ourpipes-0.0.5.dist-info/RECORD
