Metadata-Version: 2.1
Name: ourpipes
Version: 0.0.5
Summary: Framework for setup and running functions asynchronously in topological order.
Home-page: UNKNOWN
Author: Rikard Olsson
Author-email: rikard@ourstudio.se
License: UNKNOWN
Platform: UNKNOWN
License-File: LICENSE
Requires-Dist: toposort (==1.6)
